{"Model":0,"Textures":null,"Textures2":null,"TextureFiles":{"24674":[{"FileDataId":150098,"Gender":3,"Class":0,"Race":0,"ExtraData":0}],"27531":[{"FileDataId":151990,"Gender":3,"Class":0,"Race":0,"ExtraData":0}],"43593":[{"FileDataId":164104,"Gender":3,"Class":0,"Race":0,"ExtraData":0}],"45773":[{"FileDataId":161424,"Gender":3,"Class":0,"Race":0,"ExtraData":0}]},"ModelFiles":null,"Item":{"Flags":0,"InventoryType":5,"ItemClass":4,"ItemSubClass":0,"HideGeosetMale":null,"HideGeosetFemale":null,"GeosetGroup":[0,0,0,0,0,0],"AttachGeosetGroup":[0,0,0,0,0,0],"ParticleColor":null},"Creature":null,"RaceFlags":0,"Race":0,"Gender":0,"ItemEffects":null,"Equipment":null,"ComponentTextures":{"0":27531,"1":24674,"3":43593,"4":45773},"ComponentModels":null,"stateKit":null,"stateKits":null,"Scale":1}