{"Model":0,"Textures":null,"Textures2":null,"TextureFiles":{"26103":[{"FileDataId":149696,"Gender":3,"Class":0,"Race":0,"ExtraData":0}],"31812":[{"FileDataId":154181,"Gender":3,"Class":0,"Race":0,"ExtraData":0}]},"ModelFiles":null,"Item":{"Flags":0,"InventoryType":10,"ItemClass":4,"ItemSubClass":2,"HideGeosetMale":null,"HideGeosetFemale":null,"GeosetGroup":[0,0,0,0,0,0],"AttachGeosetGroup":[0,0,0,0,0,0],"ParticleColor":null},"Creature":null,"RaceFlags":0,"Race":0,"Gender":0,"ItemEffects":null,"Equipment":null,"ComponentTextures":{"1":26103,"2":31812},"ComponentModels":null,"stateKit":null,"stateKits":null,"Scale":1}