{"Model":0,"Textures":{"0":336817,"1":336817,"2":336817},"Textures2":null,"TextureFiles":null,"ModelFiles":{"2195":[{"FileDataId":336820,"Gender":1,"Class":0,"Race":10,"ExtraData":-1},{"FileDataId":336821,"Gender":0,"Class":0,"Race":10,"ExtraData":-1},{"FileDataId":336822,"Gender":1,"Class":0,"Race":11,"ExtraData":-1},{"FileDataId":336823,"Gender":0,"Class":0,"Race":11,"ExtraData":-1},{"FileDataId":336824,"Gender":1,"Class":0,"Race":3,"ExtraData":-1},{"FileDataId":336825,"Gender":0,"Class":0,"Race":3,"ExtraData":-1},{"FileDataId":336826,"Gender":1,"Class":0,"Race":7,"ExtraData":-1},{"FileDataId":336827,"Gender":0,"Class":0,"Race":7,"ExtraData":-1},{"FileDataId":336828,"Gender":1,"Class":0,"Race":9,"ExtraData":-1},{"FileDataId":336829,"Gender":0,"Class":0,"Race":9,"ExtraData":-1},{"FileDataId":336830,"Gender":1,"Class":0,"Race":1,"ExtraData":-1},{"FileDataId":336831,"Gender":0,"Class":0,"Race":1,"ExtraData":-1},{"FileDataId":336832,"Gender":1,"Class":0,"Race":4,"ExtraData":-1},{"FileDataId":336833,"Gender":0,"Class":0,"Race":4,"ExtraData":-1},{"FileDataId":336834,"Gender":1,"Class":0,"Race":2,"ExtraData":-1},{"FileDataId":336835,"Gender":0,"Class":0,"Race":2,"ExtraData":-1},{"FileDataId":336836,"Gender":1,"Class":0,"Race":5,"ExtraData":-1},{"FileDataId":336837,"Gender":0,"Class":0,"Race":5,"ExtraData":-1},{"FileDataId":336838,"Gender":1,"Class":0,"Race":6,"ExtraData":-1},{"FileDataId":336839,"Gender":0,"Class":0,"Race":6,"ExtraData":-1},{"FileDataId":336840,"Gender":1,"Class":0,"Race":8,"ExtraData":-1},{"FileDataId":336841,"Gender":0,"Class":0,"Race":8,"ExtraData":-1},{"FileDataId":454774,"Gender":1,"Class":0,"Race":22,"ExtraData":-1},{"FileDataId":454775,"Gender":0,"Class":0,"Race":22,"ExtraData":-1},{"FileDataId":610959,"Gender":1,"Class":0,"Race":24,"ExtraData":-1},{"FileDataId":610961,"Gender":0,"Class":0,"Race":24,"ExtraData":-1},{"FileDataId":1818147,"Gender":0,"Class":0,"Race":31,"ExtraData":-1},{"FileDataId":2742404,"Gender":0,"Class":0,"Race":32,"ExtraData":-1},{"FileDataId":2742405,"Gender":1,"Class":0,"Race":32,"ExtraData":-1},{"FileDataId":3167907,"Gender":0,"Class":0,"Race":35,"ExtraData":-1},{"FileDataId":3167908,"Gender":1,"Class":0,"Race":35,"ExtraData":-1}]},"Item":{"Flags":0,"InventoryType":1,"ItemClass":4,"ItemSubClass":2,"HideGeosetMale":[{"RaceId":1,"GeosetGroup":0,"RaceBitSelection":0},{"RaceId":2,"GeosetGroup":0,"RaceBitSelection":0},{"RaceId":3,"GeosetGroup":0,"RaceBitSelection":0},{"RaceId":4,"GeosetGroup":0,"RaceBitSelection":0},{"RaceId":5,"GeosetGroup":0,"RaceBitSelection":0},{"RaceId":7,"GeosetGroup":0,"RaceBitSelection":0},{"RaceId":8,"GeosetGroup":0,"RaceBitSelection":0},{"RaceId":9,"GeosetGroup":0,"RaceBitSelection":0},{"RaceId":10,"GeosetGroup":0,"RaceBitSelection":0},{"RaceId":11,"GeosetGroup":0,"RaceBitSelection":0},{"RaceId":22,"GeosetGroup":0,"RaceBitSelection":0},{"RaceId":23,"GeosetGroup":0,"RaceBitSelection":0},{"RaceId":24,"GeosetGroup":0,"RaceBitSelection":0},{"RaceId":25,"GeosetGroup":0,"RaceBitSelection":0},{"RaceId":26,"GeosetGroup":0,"RaceBitSelection":0},{"RaceId":27,"GeosetGroup":0,"RaceBitSelection":0},{"RaceId":29,"GeosetGroup":0,"RaceBitSelection":0},{"RaceId":30,"GeosetGroup":0,"RaceBitSelection":0},{"RaceId":32,"GeosetGroup":0,"RaceBitSelection":0},{"RaceId":33,"GeosetGroup":0,"RaceBitSelection":0},{"RaceId":34,"GeosetGroup":0,"RaceBitSelection":0},{"RaceId":35,"GeosetGroup":0,"RaceBitSelection":0},{"RaceId":36,"GeosetGroup":0,"RaceBitSelection":0},{"RaceId":1,"GeosetGroup":1,"RaceBitSelection":0},{"RaceId":2,"GeosetGroup":1,"RaceBitSelection":0},{"RaceId":3,"GeosetGroup":1,"RaceBitSelection":0},{"RaceId":4,"GeosetGroup":1,"RaceBitSelection":0},{"RaceId":5,"GeosetGroup":1,"RaceBitSelection":0},{"RaceId":6,"GeosetGroup":1,"RaceBitSelection":0},{"RaceId":7,"GeosetGroup":1,"RaceBitSelection":0},{"RaceId":8,"GeosetGroup":1,"RaceBitSelection":0},{"RaceId":10,"GeosetGroup":1,"RaceBitSelection":0},{"RaceId":22,"GeosetGroup":1,"RaceBitSelection":0},{"RaceId":23,"GeosetGroup":1,"RaceBitSelection":0},{"RaceId":24,"GeosetGroup":1,"RaceBitSelection":0},{"RaceId":25,"GeosetGroup":1,"RaceBitSelection":0},{"RaceId":26,"GeosetGroup":1,"RaceBitSelection":0},{"RaceId":27,"GeosetGroup":1,"RaceBitSelection":0},{"RaceId":28,"GeosetGroup":1,"RaceBitSelection":0},{"RaceId":29,"GeosetGroup":1,"RaceBitSelection":0},{"RaceId":32,"GeosetGroup":1,"RaceBitSelection":0},{"RaceId":33,"GeosetGroup":1,"RaceBitSelection":0},{"RaceId":34,"GeosetGroup":1,"RaceBitSelection":0},{"RaceId":36,"GeosetGroup":1,"RaceBitSelection":0},{"RaceId":1,"GeosetGroup":2,"RaceBitSelection":0},{"RaceId":2,"GeosetGroup":2,"RaceBitSelection":0},{"RaceId":3,"GeosetGroup":2,"RaceBitSelection":0},{"RaceId":4,"GeosetGroup":2,"RaceBitSelection":0},{"RaceId":5,"GeosetGroup":2,"RaceBitSelection":0},{"RaceId":6,"GeosetGroup":2,"RaceBitSelection":0},{"RaceId":7,"GeosetGroup":2,"RaceBitSelection":0},{"RaceId":8,"GeosetGroup":2,"RaceBitSelection":0},{"RaceId":10,"GeosetGroup":2,"RaceBitSelection":0},{"RaceId":22,"GeosetGroup":2,"RaceBitSelection":0},{"RaceId":23,"GeosetGroup":2,"RaceBitSelection":0},{"RaceId":28,"GeosetGroup":2,"RaceBitSelection":0},{"RaceId":29,"GeosetGroup":2,"RaceBitSelection":0},{"RaceId":32,"GeosetGroup":2,"RaceBitSelection":0},{"RaceId":33,"GeosetGroup":2,"RaceBitSelection":0},{"RaceId":34,"GeosetGroup":2,"RaceBitSelection":0},{"RaceId":35,"GeosetGroup":2,"RaceBitSelection":0},{"RaceId":36,"GeosetGroup":2,"RaceBitSelection":0},{"RaceId":1,"GeosetGroup":3,"RaceBitSelection":0},{"RaceId":2,"GeosetGroup":3,"RaceBitSelection":0},{"RaceId":3,"GeosetGroup":3,"RaceBitSelection":0},{"RaceId":5,"GeosetGroup":3,"RaceBitSelection":0},{"RaceId":7,"GeosetGroup":3,"RaceBitSelection":0},{"RaceId":10,"GeosetGroup":3,"RaceBitSelection":0},{"RaceId":11,"GeosetGroup":3,"RaceBitSelection":0},{"RaceId":22,"GeosetGroup":3,"RaceBitSelection":0},{"RaceId":23,"GeosetGroup":3,"RaceBitSelection":0},{"RaceId":24,"GeosetGroup":3,"RaceBitSelection":0},{"RaceId":25,"GeosetGroup":3,"RaceBitSelection":0},{"RaceId":26,"GeosetGroup":3,"RaceBitSelection":0},{"RaceId":27,"GeosetGroup":3,"RaceBitSelection":0},{"RaceId":29,"GeosetGroup":3,"RaceBitSelection":0},{"RaceId":30,"GeosetGroup":3,"RaceBitSelection":0},{"RaceId":32,"GeosetGroup":3,"RaceBitSelection":0},{"RaceId":33,"GeosetGroup":3,"RaceBitSelection":0},{"RaceId":34,"GeosetGroup":3,"RaceBitSelection":0},{"RaceId":36,"GeosetGroup":3,"RaceBitSelection":0},{"RaceId":1,"GeosetGroup":7,"RaceBitSelection":0},{"RaceId":2,"GeosetGroup":7,"RaceBitSelection":0},{"RaceId":3,"GeosetGroup":7,"RaceBitSelection":0},{"RaceId":4,"GeosetGroup":7,"RaceBitSelection":0},{"RaceId":5,"GeosetGroup":7,"RaceBitSelection":0},{"RaceId":6,"GeosetGroup":7,"RaceBitSelection":0},{"RaceId":7,"GeosetGroup":7,"RaceBitSelection":0},{"RaceId":8,"GeosetGroup":7,"RaceBitSelection":0},{"RaceId":10,"GeosetGroup":7,"RaceBitSelection":0},{"RaceId":11,"GeosetGroup":7,"RaceBitSelection":0},{"RaceId":22,"GeosetGroup":7,"RaceBitSelection":0},{"RaceId":23,"GeosetGroup":7,"RaceBitSelection":0},{"RaceId":24,"GeosetGroup":7,"RaceBitSelection":0},{"RaceId":25,"GeosetGroup":7,"RaceBitSelection":0},{"RaceId":26,"GeosetGroup":7,"RaceBitSelection":0},{"RaceId":27,"GeosetGroup":7,"RaceBitSelection":0},{"RaceId":28,"GeosetGroup":7,"RaceBitSelection":0},{"RaceId":29,"GeosetGroup":7,"RaceBitSelection":0},{"RaceId":30,"GeosetGroup":7,"RaceBitSelection":0},{"RaceId":32,"GeosetGroup":7,"RaceBitSelection":0},{"RaceId":33,"GeosetGroup":7,"RaceBitSelection":0},{"RaceId":34,"GeosetGroup":7,"RaceBitSelection":0},{"RaceId":35,"GeosetGroup":7,"RaceBitSelection":0},{"RaceId":36,"GeosetGroup":7,"RaceBitSelection":0},{"RaceId":8,"GeosetGroup":16,"RaceBitSelection":0},{"RaceId":30,"GeosetGroup":16,"RaceBitSelection":0},{"RaceId":4,"GeosetGroup":25,"RaceBitSelection":0},{"RaceId":10,"GeosetGroup":25,"RaceBitSelection":0},{"RaceId":27,"GeosetGroup":25,"RaceBitSelection":0},{"RaceId":29,"GeosetGroup":25,"RaceBitSelection":0},{"RaceId":31,"GeosetGroup":0,"RaceBitSelection":0},{"RaceId":31,"GeosetGroup":1,"RaceBitSelection":0},{"RaceId":31,"GeosetGroup":16,"RaceBitSelection":0},{"RaceId":37,"GeosetGroup":0,"RaceBitSelection":0},{"RaceId":37,"GeosetGroup":1,"RaceBitSelection":0},{"RaceId":37,"GeosetGroup":2,"RaceBitSelection":0},{"RaceId":37,"GeosetGroup":3,"RaceBitSelection":0},{"RaceId":37,"GeosetGroup":7,"RaceBitSelection":0},{"RaceId":37,"GeosetGroup":24,"RaceBitSelection":0},{"RaceId":37,"GeosetGroup":16,"RaceBitSelection":0},{"RaceId":37,"GeosetGroup":17,"RaceBitSelection":0},{"RaceId":37,"GeosetGroup":25,"RaceBitSelection":0},{"RaceId":4,"GeosetGroup":34,"RaceBitSelection":0},{"RaceId":6,"GeosetGroup":24,"RaceBitSelection":0},{"RaceId":6,"GeosetGroup":16,"RaceBitSelection":0},{"RaceId":8,"GeosetGroup":40,"RaceBitSelection":0},{"RaceId":9,"GeosetGroup":40,"RaceBitSelection":0},{"RaceId":9,"GeosetGroup":7,"RaceBitSelection":0},{"RaceId":9,"GeosetGroup":41,"RaceBitSelection":0},{"RaceId":11,"GeosetGroup":2,"RaceBitSelection":0},{"RaceId":11,"GeosetGroup":1,"RaceBitSelection":0},{"RaceId":24,"GeosetGroup":34,"RaceBitSelection":0},{"RaceId":25,"GeosetGroup":34,"RaceBitSelection":0},{"RaceId":26,"GeosetGroup":34,"RaceBitSelection":0},{"RaceId":27,"GeosetGroup":35,"RaceBitSelection":0},{"RaceId":28,"GeosetGroup":24,"RaceBitSelection":0},{"RaceId":28,"GeosetGroup":16,"RaceBitSelection":0},{"RaceId":30,"GeosetGroup":2,"RaceBitSelection":0},{"RaceId":30,"GeosetGroup":1,"RaceBitSelection":0},{"RaceId":31,"GeosetGroup":7,"RaceBitSelection":0},{"RaceId":31,"GeosetGroup":40,"RaceBitSelection":0},{"RaceId":35,"GeosetGroup":35,"RaceBitSelection":0},{"RaceId":35,"GeosetGroup":41,"RaceBitSelection":0},{"RaceId":2,"GeosetGroup":35,"RaceBitSelection":0},{"RaceId":3,"GeosetGroup":35,"RaceBitSelection":0},{"RaceId":4,"GeosetGroup":39,"RaceBitSelection":0},{"RaceId":6,"GeosetGroup":0,"RaceBitSelection":0},{"RaceId":6,"GeosetGroup":39,"RaceBitSelection":0},{"RaceId":6,"GeosetGroup":37,"RaceBitSelection":0},{"RaceId":7,"GeosetGroup":34,"RaceBitSelection":0},{"RaceId":9,"GeosetGroup":35,"RaceBitSelection":0},{"RaceId":11,"GeosetGroup":39,"RaceBitSelection":0},{"RaceId":4,"GeosetGroup":3,"RaceBitSelection":0},{"RaceId":11,"GeosetGroup":24,"RaceBitSelection":0},{"RaceId":8,"GeosetGroup":35,"RaceBitSelection":0},{"RaceId":11,"GeosetGroup":37,"RaceBitSelection":0},{"RaceId":10,"GeosetGroup":35,"RaceBitSelection":0},{"RaceId":7,"GeosetGroup":35,"RaceBitSelection":0},{"RaceId":34,"GeosetGroup":35,"RaceBitSelection":0},{"RaceId":36,"GeosetGroup":35,"RaceBitSelection":0},{"RaceId":4,"GeosetGroup":35,"RaceBitSelection":0},{"RaceId":25,"GeosetGroup":35,"RaceBitSelection":0},{"RaceId":26,"GeosetGroup":35,"RaceBitSelection":0},{"RaceId":24,"GeosetGroup":35,"RaceBitSelection":0},{"RaceId":6,"GeosetGroup":35,"RaceBitSelection":0},{"RaceId":2,"GeosetGroup":34,"RaceBitSelection":0},{"RaceId":29,"GeosetGroup":35,"RaceBitSelection":0},{"RaceId":31,"GeosetGroup":35,"RaceBitSelection":0},{"RaceId":1,"GeosetGroup":35,"RaceBitSelection":0},{"RaceId":32,"GeosetGroup":35,"RaceBitSelection":0},{"RaceId":30,"GeosetGroup":35,"RaceBitSelection":0},{"RaceId":28,"GeosetGroup":35,"RaceBitSelection":0},{"RaceId":3,"GeosetGroup":34,"RaceBitSelection":0},{"RaceId":1,"GeosetGroup":34,"RaceBitSelection":0},{"RaceId":30,"GeosetGroup":34,"RaceBitSelection":0},{"RaceId":30,"GeosetGroup":24,"RaceBitSelection":0},{"RaceId":4,"GeosetGroup":37,"RaceBitSelection":0},{"RaceId":30,"GeosetGroup":39,"RaceBitSelection":0},{"RaceId":27,"GeosetGroup":34,"RaceBitSelection":0},{"RaceId":27,"GeosetGroup":37,"RaceBitSelection":0},{"RaceId":29,"GeosetGroup":24,"RaceBitSelection":0},{"RaceId":28,"GeosetGroup":0,"RaceBitSelection":0},{"RaceId":28,"GeosetGroup":37,"RaceBitSelection":0},{"RaceId":28,"GeosetGroup":42,"RaceBitSelection":0},{"RaceId":28,"GeosetGroup":43,"RaceBitSelection":0},{"RaceId":28,"GeosetGroup":39,"RaceBitSelection":0},{"RaceId":27,"GeosetGroup":2,"RaceBitSelection":0},{"RaceId":27,"GeosetGroup":39,"RaceBitSelection":0}],"HideGeosetFemale":[{"RaceId":1,"GeosetGroup":0,"RaceBitSelection":0},{"RaceId":2,"GeosetGroup":0,"RaceBitSelection":0},{"RaceId":3,"GeosetGroup":0,"RaceBitSelection":0},{"RaceId":4,"GeosetGroup":0,"RaceBitSelection":0},{"RaceId":5,"GeosetGroup":0,"RaceBitSelection":0},{"RaceId":7,"GeosetGroup":0,"RaceBitSelection":0},{"RaceId":8,"GeosetGroup":0,"RaceBitSelection":0},{"RaceId":9,"GeosetGroup":0,"RaceBitSelection":0},{"RaceId":10,"GeosetGroup":0,"RaceBitSelection":0},{"RaceId":11,"GeosetGroup":0,"RaceBitSelection":0},{"RaceId":22,"GeosetGroup":0,"RaceBitSelection":0},{"RaceId":23,"GeosetGroup":0,"RaceBitSelection":0},{"RaceId":24,"GeosetGroup":0,"RaceBitSelection":0},{"RaceId":25,"GeosetGroup":0,"RaceBitSelection":0},{"RaceId":26,"GeosetGroup":0,"RaceBitSelection":0},{"RaceId":27,"GeosetGroup":0,"RaceBitSelection":0},{"RaceId":29,"GeosetGroup":0,"RaceBitSelection":0},{"RaceId":30,"GeosetGroup":0,"RaceBitSelection":0},{"RaceId":32,"GeosetGroup":0,"RaceBitSelection":0},{"RaceId":33,"GeosetGroup":0,"RaceBitSelection":0},{"RaceId":34,"GeosetGroup":0,"RaceBitSelection":0},{"RaceId":35,"GeosetGroup":0,"RaceBitSelection":0},{"RaceId":36,"GeosetGroup":0,"RaceBitSelection":0},{"RaceId":1,"GeosetGroup":1,"RaceBitSelection":0},{"RaceId":2,"GeosetGroup":1,"RaceBitSelection":0},{"RaceId":3,"GeosetGroup":1,"RaceBitSelection":0},{"RaceId":4,"GeosetGroup":1,"RaceBitSelection":0},{"RaceId":5,"GeosetGroup":1,"RaceBitSelection":0},{"RaceId":6,"GeosetGroup":1,"RaceBitSelection":0},{"RaceId":7,"GeosetGroup":1,"RaceBitSelection":0},{"RaceId":8,"GeosetGroup":1,"RaceBitSelection":0},{"RaceId":10,"GeosetGroup":1,"RaceBitSelection":0},{"RaceId":22,"GeosetGroup":1,"RaceBitSelection":0},{"RaceId":23,"GeosetGroup":1,"RaceBitSelection":0},{"RaceId":24,"GeosetGroup":1,"RaceBitSelection":0},{"RaceId":25,"GeosetGroup":1,"RaceBitSelection":0},{"RaceId":26,"GeosetGroup":1,"RaceBitSelection":0},{"RaceId":27,"GeosetGroup":1,"RaceBitSelection":0},{"RaceId":28,"GeosetGroup":1,"RaceBitSelection":0},{"RaceId":29,"GeosetGroup":1,"RaceBitSelection":0},{"RaceId":32,"GeosetGroup":1,"RaceBitSelection":0},{"RaceId":33,"GeosetGroup":1,"RaceBitSelection":0},{"RaceId":34,"GeosetGroup":1,"RaceBitSelection":0},{"RaceId":36,"GeosetGroup":1,"RaceBitSelection":0},{"RaceId":1,"GeosetGroup":2,"RaceBitSelection":0},{"RaceId":2,"GeosetGroup":2,"RaceBitSelection":0},{"RaceId":3,"GeosetGroup":2,"RaceBitSelection":0},{"RaceId":4,"GeosetGroup":2,"RaceBitSelection":0},{"RaceId":5,"GeosetGroup":2,"RaceBitSelection":0},{"RaceId":6,"GeosetGroup":2,"RaceBitSelection":0},{"RaceId":7,"GeosetGroup":2,"RaceBitSelection":0},{"RaceId":8,"GeosetGroup":2,"RaceBitSelection":0},{"RaceId":10,"GeosetGroup":2,"RaceBitSelection":0},{"RaceId":22,"GeosetGroup":2,"RaceBitSelection":0},{"RaceId":23,"GeosetGroup":2,"RaceBitSelection":0},{"RaceId":28,"GeosetGroup":2,"RaceBitSelection":0},{"RaceId":29,"GeosetGroup":2,"RaceBitSelection":0},{"RaceId":32,"GeosetGroup":2,"RaceBitSelection":0},{"RaceId":33,"GeosetGroup":2,"RaceBitSelection":0},{"RaceId":34,"GeosetGroup":2,"RaceBitSelection":0},{"RaceId":35,"GeosetGroup":2,"RaceBitSelection":0},{"RaceId":36,"GeosetGroup":2,"RaceBitSelection":0},{"RaceId":1,"GeosetGroup":3,"RaceBitSelection":0},{"RaceId":2,"GeosetGroup":3,"RaceBitSelection":0},{"RaceId":3,"GeosetGroup":3,"RaceBitSelection":0},{"RaceId":5,"GeosetGroup":3,"RaceBitSelection":0},{"RaceId":7,"GeosetGroup":3,"RaceBitSelection":0},{"RaceId":10,"GeosetGroup":3,"RaceBitSelection":0},{"RaceId":11,"GeosetGroup":3,"RaceBitSelection":0},{"RaceId":22,"GeosetGroup":3,"RaceBitSelection":0},{"RaceId":23,"GeosetGroup":3,"RaceBitSelection":0},{"RaceId":24,"GeosetGroup":3,"RaceBitSelection":0},{"RaceId":25,"GeosetGroup":3,"RaceBitSelection":0},{"RaceId":26,"GeosetGroup":3,"RaceBitSelection":0},{"RaceId":27,"GeosetGroup":3,"RaceBitSelection":0},{"RaceId":29,"GeosetGroup":3,"RaceBitSelection":0},{"RaceId":30,"GeosetGroup":3,"RaceBitSelection":0},{"RaceId":32,"GeosetGroup":3,"RaceBitSelection":0},{"RaceId":33,"GeosetGroup":3,"RaceBitSelection":0},{"RaceId":34,"GeosetGroup":3,"RaceBitSelection":0},{"RaceId":36,"GeosetGroup":3,"RaceBitSelection":0},{"RaceId":1,"GeosetGroup":7,"RaceBitSelection":0},{"RaceId":2,"GeosetGroup":7,"RaceBitSelection":0},{"RaceId":3,"GeosetGroup":7,"RaceBitSelection":0},{"RaceId":4,"GeosetGroup":7,"RaceBitSelection":0},{"RaceId":5,"GeosetGroup":7,"RaceBitSelection":0},{"RaceId":6,"GeosetGroup":7,"RaceBitSelection":0},{"RaceId":7,"GeosetGroup":7,"RaceBitSelection":0},{"RaceId":8,"GeosetGroup":7,"RaceBitSelection":0},{"RaceId":10,"GeosetGroup":7,"RaceBitSelection":0},{"RaceId":11,"GeosetGroup":7,"RaceBitSelection":0},{"RaceId":22,"GeosetGroup":7,"RaceBitSelection":0},{"RaceId":23,"GeosetGroup":7,"RaceBitSelection":0},{"RaceId":24,"GeosetGroup":7,"RaceBitSelection":0},{"RaceId":25,"GeosetGroup":7,"RaceBitSelection":0},{"RaceId":26,"GeosetGroup":7,"RaceBitSelection":0},{"RaceId":27,"GeosetGroup":7,"RaceBitSelection":0},{"RaceId":28,"GeosetGroup":7,"RaceBitSelection":0},{"RaceId":29,"GeosetGroup":7,"RaceBitSelection":0},{"RaceId":30,"GeosetGroup":7,"RaceBitSelection":0},{"RaceId":32,"GeosetGroup":7,"RaceBitSelection":0},{"RaceId":33,"GeosetGroup":7,"RaceBitSelection":0},{"RaceId":34,"GeosetGroup":7,"RaceBitSelection":0},{"RaceId":35,"GeosetGroup":7,"RaceBitSelection":0},{"RaceId":36,"GeosetGroup":7,"RaceBitSelection":0},{"RaceId":8,"GeosetGroup":16,"RaceBitSelection":0},{"RaceId":30,"GeosetGroup":16,"RaceBitSelection":0},{"RaceId":4,"GeosetGroup":25,"RaceBitSelection":0},{"RaceId":10,"GeosetGroup":25,"RaceBitSelection":0},{"RaceId":27,"GeosetGroup":25,"RaceBitSelection":0},{"RaceId":29,"GeosetGroup":25,"RaceBitSelection":0},{"RaceId":31,"GeosetGroup":0,"RaceBitSelection":0},{"RaceId":31,"GeosetGroup":1,"RaceBitSelection":0},{"RaceId":31,"GeosetGroup":16,"RaceBitSelection":0},{"RaceId":37,"GeosetGroup":0,"RaceBitSelection":0},{"RaceId":37,"GeosetGroup":1,"RaceBitSelection":0},{"RaceId":37,"GeosetGroup":2,"RaceBitSelection":0},{"RaceId":37,"GeosetGroup":3,"RaceBitSelection":0},{"RaceId":37,"GeosetGroup":7,"RaceBitSelection":0},{"RaceId":37,"GeosetGroup":24,"RaceBitSelection":0},{"RaceId":37,"GeosetGroup":16,"RaceBitSelection":0},{"RaceId":37,"GeosetGroup":17,"RaceBitSelection":0},{"RaceId":37,"GeosetGroup":25,"RaceBitSelection":0},{"RaceId":4,"GeosetGroup":34,"RaceBitSelection":0},{"RaceId":6,"GeosetGroup":24,"RaceBitSelection":0},{"RaceId":6,"GeosetGroup":16,"RaceBitSelection":0},{"RaceId":8,"GeosetGroup":40,"RaceBitSelection":0},{"RaceId":9,"GeosetGroup":40,"RaceBitSelection":0},{"RaceId":9,"GeosetGroup":7,"RaceBitSelection":0},{"RaceId":9,"GeosetGroup":41,"RaceBitSelection":0},{"RaceId":11,"GeosetGroup":2,"RaceBitSelection":0},{"RaceId":11,"GeosetGroup":1,"RaceBitSelection":0},{"RaceId":24,"GeosetGroup":34,"RaceBitSelection":0},{"RaceId":25,"GeosetGroup":34,"RaceBitSelection":0},{"RaceId":26,"GeosetGroup":34,"RaceBitSelection":0},{"RaceId":27,"GeosetGroup":35,"RaceBitSelection":0},{"RaceId":28,"GeosetGroup":24,"RaceBitSelection":0},{"RaceId":28,"GeosetGroup":16,"RaceBitSelection":0},{"RaceId":30,"GeosetGroup":2,"RaceBitSelection":0},{"RaceId":30,"GeosetGroup":1,"RaceBitSelection":0},{"RaceId":31,"GeosetGroup":7,"RaceBitSelection":0},{"RaceId":31,"GeosetGroup":40,"RaceBitSelection":0},{"RaceId":35,"GeosetGroup":35,"RaceBitSelection":0},{"RaceId":35,"GeosetGroup":41,"RaceBitSelection":0},{"RaceId":2,"GeosetGroup":35,"RaceBitSelection":0},{"RaceId":3,"GeosetGroup":35,"RaceBitSelection":0},{"RaceId":4,"GeosetGroup":39,"RaceBitSelection":0},{"RaceId":6,"GeosetGroup":0,"RaceBitSelection":0},{"RaceId":6,"GeosetGroup":39,"RaceBitSelection":0},{"RaceId":6,"GeosetGroup":37,"RaceBitSelection":0},{"RaceId":7,"GeosetGroup":34,"RaceBitSelection":0},{"RaceId":9,"GeosetGroup":35,"RaceBitSelection":0},{"RaceId":11,"GeosetGroup":39,"RaceBitSelection":0},{"RaceId":4,"GeosetGroup":3,"RaceBitSelection":0},{"RaceId":11,"GeosetGroup":24,"RaceBitSelection":0},{"RaceId":8,"GeosetGroup":35,"RaceBitSelection":0},{"RaceId":11,"GeosetGroup":37,"RaceBitSelection":0},{"RaceId":10,"GeosetGroup":35,"RaceBitSelection":0},{"RaceId":7,"GeosetGroup":35,"RaceBitSelection":0},{"RaceId":34,"GeosetGroup":35,"RaceBitSelection":0},{"RaceId":36,"GeosetGroup":35,"RaceBitSelection":0},{"RaceId":4,"GeosetGroup":35,"RaceBitSelection":0},{"RaceId":25,"GeosetGroup":35,"RaceBitSelection":0},{"RaceId":26,"GeosetGroup":35,"RaceBitSelection":0},{"RaceId":24,"GeosetGroup":35,"RaceBitSelection":0},{"RaceId":6,"GeosetGroup":35,"RaceBitSelection":0},{"RaceId":2,"GeosetGroup":34,"RaceBitSelection":0},{"RaceId":29,"GeosetGroup":35,"RaceBitSelection":0},{"RaceId":31,"GeosetGroup":35,"RaceBitSelection":0},{"RaceId":1,"GeosetGroup":35,"RaceBitSelection":0},{"RaceId":32,"GeosetGroup":35,"RaceBitSelection":0},{"RaceId":30,"GeosetGroup":35,"RaceBitSelection":0},{"RaceId":28,"GeosetGroup":35,"RaceBitSelection":0},{"RaceId":3,"GeosetGroup":34,"RaceBitSelection":0},{"RaceId":1,"GeosetGroup":34,"RaceBitSelection":0},{"RaceId":30,"GeosetGroup":34,"RaceBitSelection":0},{"RaceId":30,"GeosetGroup":24,"RaceBitSelection":0},{"RaceId":4,"GeosetGroup":37,"RaceBitSelection":0},{"RaceId":30,"GeosetGroup":39,"RaceBitSelection":0},{"RaceId":27,"GeosetGroup":34,"RaceBitSelection":0},{"RaceId":27,"GeosetGroup":37,"RaceBitSelection":0},{"RaceId":29,"GeosetGroup":24,"RaceBitSelection":0},{"RaceId":28,"GeosetGroup":0,"RaceBitSelection":0},{"RaceId":28,"GeosetGroup":37,"RaceBitSelection":0},{"RaceId":28,"GeosetGroup":42,"RaceBitSelection":0},{"RaceId":28,"GeosetGroup":43,"RaceBitSelection":0},{"RaceId":28,"GeosetGroup":39,"RaceBitSelection":0},{"RaceId":27,"GeosetGroup":2,"RaceBitSelection":0},{"RaceId":27,"GeosetGroup":39,"RaceBitSelection":0}],"GeosetGroup":[0,0,0,0,0,0],"AttachGeosetGroup":[0,0,0,0,0,0],"ParticleColor":{"Id":561,"Start":[4293456698,4278190080,4278190080],"Mid":[4285051663,4278190080,4278190080],"End":[4284033321,4278190080,4278190080]}},"Creature":null,"RaceFlags":0,"Race":0,"Gender":0,"ItemEffects":null,"Equipment":null,"ComponentTextures":null,"ComponentModels":{"0":2195},"stateKit":null,"stateKits":null,"Scale":1}